GUI/__init__.py
GUI/account_created.py
GUI/add_new_column.py
GUI/add_new_row.py
GUI/delete_column.py
GUI/filter_col_data.py
GUI/login_failed.py
GUI/login_succes.py
GUI/login_window.py
GUI/main_menu_window.py
GUI/plot_bokeh.py
GUI/plot_mat.py
GUI/register_user.py
GUI/rename_column.py
GUI/select_multiple_col.py
GUI/show_column_data.py
GUI/show_row_data.py
GUI/split_col_data.py
GUI/sum_columns.py
GUI/weather.py
_legacy_/__init__.py
_legacy_/dataframe_operations.py
_legacy_/weather_selenium.py
_legacy_/web_api/__init__.py
_legacy_/web_api/connect_api.py
_legacy_/webscrapping/__init__.py
_legacy_/webscrapping/accuweather.py
_legacy_/webscrapping/output_data/__init__.py
input_data/__init__.py
output_data/__init__.py
PandasDataFrame-1.0.2.dist-info/LICENSE.txt
PandasDataFrame-1.0.2.dist-info/METADATA
PandasDataFrame-1.0.2.dist-info/WHEEL
PandasDataFrame-1.0.2.dist-info/top_level.txt
PandasDataFrame-1.0.2.dist-info/RECORD
