Metadata-Version: 2.1
Name: PandasDataFrame
Version: 1.0.2
Summary: Pandas DataFrame Application
Home-page: https://github.com/Boschetzel/PandasDataFrame.git
Author: Boschetzel (Bogdan Fometescu)
Author-email: <mbogdan.fometescu@gmail.com>
Keywords: python,dataframe,pandas,selenium
Classifier: Development Status :: 1 - Planning
Classifier: Intended Audience :: Developers
Classifier: Programming Language :: Python :: 3
Classifier: Operating System :: Unix
Classifier: Operating System :: MacOS :: MacOS X
Classifier: Operating System :: Microsoft :: Windows
License-File: LICENSE.txt
Requires-Dist: selenium
Requires-Dist: bokeh
Requires-Dist: requests
Requires-Dist: matplotlib
Requires-Dist: pyqt5
